setup.py
DarkFream/__init__.py
DarkFream/app.py
DarkFream/main.py
DarkFream/models.py
DarkFream/template.py
DarkFream/urls.py
DarkFream.egg-info/PKG-INFO
DarkFream.egg-info/SOURCES.txt
DarkFream.egg-info/dependency_links.txt
DarkFream.egg-info/entry_points.txt
DarkFream.egg-info/requires.txt
DarkFream.egg-info/top_level.txt