Metadata-Version: 2.1
Name: DarkFream
Version: 1.3
Summary: My Python library
Home-page: UNKNOWN
Author: vsp210
Author-email: vsp210@gmail.com
License: UNKNOWN
Platform: UNKNOWN
